vertdetach/__init__.py
vertdetach/vertdetach.py
vertdetach-1.0.2.dist-info/LICENSE
vertdetach-1.0.2.dist-info/WHEEL
vertdetach-1.0.2.dist-info/METADATA
vertdetach-1.0.2.dist-info/RECORD
