Metadata-Version: 2.1
Name: vertdetach
Version: 1.0.2
Summary: DETACH (Device Temperature and Acceleration Change) algorithm for detecting non-wear from raw accelerometer data.
Home-page: https://github.com/actigraph/vertdetach
License: MIT
Author: Adam Vert
Author-email: vertadam@gmail.com
Maintainer: Ali Neishabouri
Maintainer-email: ali.neishabouri@theactigraph.com
Requires-Python: >=3.8.1,<3.12
Classifier: License :: OSI Approved :: MIT License
Classifier: Programming Language :: Python :: 3
Classifier: Programming Language :: Python :: 3.9
Classifier: Programming Language :: Python :: 3.10
Requires-Dist: numpy (>=1.23.3)
Requires-Dist: pandas (>=1.2.5)
Requires-Dist: scipy (>=1.7.3)
Project-URL: Repository, https://github.com/actigraph/vertdetach
